Verilog/Day 58 Parametrized Sequence Detector/parameterized_seq_detector.v
module parameterized_seq_detector #(
    parameter LEN_OF_SEQ = 4,
    parameter [LEN_OF_SEQ-1:0] SEQ = 4'b1010
)(
    input clk,
    input rst,  
    input serial_in_bit,
    output reg detected
);

reg [LEN_OF_SEQ-1:0] shift_reg;

always @(posedge clk) begin
    if (!rst) begin 
        shift_reg <= 0;
        detected <= 0;
    end else begin
        shift_reg <= {shift_reg[LEN_OF_SEQ-2:0], serial_in_bit};
        if ({shift_reg[LEN_OF_SEQ-2:0], serial_in_bit} == SEQ)
            detected <= 1;
        else
            detected <= 0;
    end
end

endmodule

Verilog/Day 58 Parametrized Sequence Detector/parameterized_seq_detector_tb.v
`timescale 1ns/1ps
module tb_parameterized_seq_detector;
    reg clk;
    reg rst;  
    reg serial_in_bit;
    wire detected;
    parameter LEN = 4;
    parameter SEQ_VAL = 4'b1010;
    parameterized_seq_detector #(LEN, SEQ_VAL) dut (
        .clk(clk),
        .rst(rst),
        .serial_in_bit(serial_in_bit),
        .detected(detected)
    );
    initial clk = 0;
    always #5 clk = ~clk;
    reg [63:0] test_pattern; 
    integer i;
    initial begin
        rst = 0;
        serial_in_bit = 0;
        #15 rst = 1;
        test_pattern = 64'hA5A5_5A5A_F0F0_0FF0_F00F_3333_5555_AAAA;
        for (i = 63; i >= 0; i = i - 1) begin
            @(posedge clk);
            serial_in_bit = test_pattern[i];
        end

        #20 $finish;
    end
    initial begin
        $monitor("Time=%0t rst=%b bin=%b detected=%b shift_reg=%b",
                 $time, rst, serial_in_bit, detected, dut.shift_reg);
    end
    initial begin
        $dumpfile("waveform.vcd");
        $dumpvars(0, tb_parameterized_seq_detector);
        $dumpvars(1, tb_parameterized_seq_detector.dut.shift_reg); // Explicit path for the shift register
    end


endmodule

Verilog/Day 58 Parametrized Sequence Detector/waveform.vcd
$date
	Mon Aug 18 11:54:18 2025
$end
$version
	QuestaSim Version 10.7c
$end
$timescale
	1ps
$end

$scope module tb_parameterized_seq_detector $end
$var parameter 32 ! LEN $end
$var parameter 4 " SEQ_VAL $end
$var reg 1 # clk $end
$var reg 1 $ rst $end
$var reg 1 % serial_in_bit $end
$var wire 1 & detected $end
$var reg 64 ' test_pattern [63:0] $end
$var integer 32 ( i $end

$scope module dut $end
$var parameter 32 ) LEN_OF_SEQ $end
$var parameter 4 * SEQ $end
$var wire 1 + clk $end
$var wire 1 , rst $end
$var wire 1 - serial_in_bit $end
$var reg 1 . detected $end
$var reg 4 / shift_reg [3:0] $end
$upscope $end
$upscope $end
$enddefinitions $end
#0
$dumpvars
0#
0$
0%
x.
bx /
bx '
b100 !
b1010 "
b100 )
b1010 *
bx (
x&
0-
0,
0+
$end
#5000
1#
1+
b0 /
0.
0&
#10000
0#
0+
#15000
1$
b1111000000001111001100110011001101010101010101011010101010101010 '
b111111 (
1#
1,
1+
1%
b111110 (
1-
#20000
0#
0+
#25000
1#
1+
b111101 (
b1 /
#30000
0#
0+
#35000
1#
1+
b111100 (
b11 /
#40000
0#
0+
#45000
1#
1+
b111011 (
b111 /
#50000
0#
0+
#55000
1#
1+
0%
b111010 (
0-
b1111 /
#60000
0#
0+
#65000
1#
1+
b111001 (
b1110 /
#70000
0#
0+
#75000
1#
1+
b111000 (
b1100 /
#80000
0#
0+
#85000
1#
1+
b110111 (
b1000 /
#90000
0#
0+
#95000
1#
1+
b110110 (
b0 /
#100000
0#
0+
#105000
1#
1+
b110101 (
#110000
0#
0+
#115000
1#
1+
b110100 (
#120000
0#
0+
#125000
1#
1+
b110011 (
#130000
0#
0+
#135000
1#
1+
1%
b110010 (
1-
#140000
0#
0+
#145000
1#
1+
b110001 (
b1 /
#150000
0#
0+
#155000
1#
1+
b110000 (
b11 /
#160000
0#
0+
#165000
1#
1+
b101111 (
b111 /
#170000
0#
0+
#175000
1#
1+
0%
b101110 (
0-
b1111 /
#180000
0#
0+
#185000
1#
1+
b101101 (
b1110 /
#190000
0#
0+
#195000
1#
1+
1%
b101100 (
1-
b1100 /
#200000
0#
0+
#205000
1#
1+
b101011 (
b1001 /
#210000
0#
0+
#215000
1#
1+
0%
b101010 (
0-
b11 /
#220000
0#
0+
#225000
1#
1+
b101001 (
b110 /
#230000
0#
0+
#235000
1#
1+
1%
b101000 (
1-
b1100 /
#240000
0#
0+
#245000
1#
1+
b100111 (
b1001 /
#250000
0#
0+
#255000
1#
1+
0%
b100110 (
0-
b11 /
#260000
0#
0+
#265000
1#
1+
b100101 (
b110 /
#270000
0#
0+
#275000
1#
1+
1%
b100100 (
1-
b1100 /
#280000
0#
0+
#285000
1#
1+
b100011 (
b1001 /
#290000
0#
0+
#295000
1#
1+
0%
b100010 (
0-
b11 /
#300000
0#
0+
#305000
1#
1+
b100001 (
b110 /
#310000
0#
0+
#315000
1#
1+
1%
b100000 (
1-
b1100 /
#320000
0#
0+
#325000
1#
1+
b11111 (
b1001 /
#330000
0#
0+
#335000
1#
1+
0%
b11110 (
0-
b11 /
#340000
0#
0+
#345000
1#
1+
1%
b11101 (
1-
b110 /
#350000
0#
0+
#355000
1#
1+
0%
b11100 (
0-
b1101 /
#360000
0#
0+
#365000
1#
1+
1%
b11011 (
1-
b1010 /
1.
1&
#370000
0#
0+
#375000
1#
1+
0%
b11010 (
0-
b101 /
0.
0&
#380000
0#
0+
#385000
1#
1+
1%
b11001 (
1-
b1010 /
1.
1&
#390000
0#
0+
#395000
1#
1+
0%
b11000 (
0-
b101 /
0.
0&
#400000
0#
0+
#405000
1#
1+
1%
b10111 (
1-
b1010 /
1.
1&
#410000
0#
0+
#415000
1#
1+
0%
b10110 (
0-
b101 /
0.
0&
#420000
0#
0+
#425000
1#
1+
1%
b10101 (
1-
b1010 /
1.
1&
#430000
0#
0+
#435000
1#
1+
0%
b10100 (
0-
b101 /
0.
0&
#440000
0#
0+
#445000
1#
1+
1%
b10011 (
1-
b1010 /
1.
1&
#450000
0#
0+
#455000
1#
1+
0%
b10010 (
0-
b101 /
0.
0&
#460000
0#
0+
#465000
1#
1+
1%
b10001 (
1-
b1010 /
1.
1&
#470000
0#
0+
#475000
1#
1+
0%
b10000 (
0-
b101 /
0.
0&
#480000
0#
0+
#485000
1#
1+
1%
b1111 (
1-
b1010 /
1.
1&
#490000
0#
0+
#495000
1#
1+
b1110 (
b101 /
0.
0&
#500000
0#
0+
#505000
1#
1+
0%
b1101 (
0-
b1011 /
#510000
0#
0+
#515000
1#
1+
1%
b1100 (
1-
b110 /
#520000
0#
0+
#525000
1#
1+
0%
b1011 (
0-
b1101 /
#530000
0#
0+
#535000
1#
1+
1%
b1010 (
1-
b1010 /
1.
1&
#540000
0#
0+
#545000
1#
1+
0%
b1001 (
0-
b101 /
0.
0&
#550000
0#
0+
#555000
1#
1+
1%
b1000 (
1-
b1010 /
1.
1&
#560000
0#
0+
#565000
1#
1+
0%
b111 (
0-
b101 /
0.
0&
#570000
0#
0+
#575000
1#
1+
1%
b110 (
1-
b1010 /
1.
1&
#580000
0#
0+
#585000
1#
1+
0%
b101 (
0-
b101 /
0.
0&
#590000
0#
0+
#595000
1#
1+
1%
b100 (
1-
b1010 /
1.
1&
#600000
0#
0+
#605000
1#
1+
0%
b11 (
0-
b101 /
0.
0&
#610000
0#
0+
#615000
1#
1+
1%
b10 (
1-
b1010 /
1.
1&
#620000
0#
0+
#625000
1#
1+
0%
b1 (
0-
b101 /
0.
0&
#630000
0#
0+
#635000
1#
1+
1%
b0 (
1-
b1010 /
1.
1&
#640000
0#
0+
#645000
1#
1+
0%
b11111111111111111111111111111111 (
0-
b101 /
0.
0&
#650000
0#
0+
#655000
1#
1+
b1010 /
1.
1&
